<?xml version="1.0" encoding="utf-8"?>
<settings>
  <version major="013" minor="001" minorblocking="True" description="If this sample config is updated in a non-breaking way the minor version should be increased, if a breaking change is introduced (a rename, a new section, etc) then the major version should be increased and the minor version should be reset."></version>
  <repolocation></repolocation>
  <username></username>
  <machinename></machinename>
  <backuplogretentiondays>30</backuplogretentiondays>
  <updatescripts>True</updatescripts>
  <displaydescriptions>True</displaydescriptions>
  <addrepostogithubdesktop>True</addrepostogithubdesktop>
  <rundismcleanmorethanonce>False</rundismcleanmorethanonce>
  <bloatwareremoval skipsection="True">
    <details>This is an experimental new feature, proceed with caution</details>
    <details   reference="https://github.com/Kugane/winget/blob/main/winget-basic.ps1"></details>
    <bloatware skip="False" id="MicrosoftTeams"           description="Microsoft Teams is a team collaboration application developed by Microsoft as part of the Microsoft 365 family of products, offering workspace chat and video conferencing, file storage, and integration of proprietary and third-party applications and services"></bloatware>
    <bloatware skip="False" id="Clipchamp.Clipchamp"      description="Clipchamp is an online video editing tool developed by Australian company Clipchamp Pty Ltd., which is now a subsidiary of Microsoft. It is non-linear editing software that allows users to import, edit, and export audiovisual material in an Internet browser window"></bloatware>
    <bloatware skip="False" id="Microsoft.OneDriveSync"   description="OneDrive is a cloud storage service from Microsoft that lets you back up, access, edit, share, and sync your files from any device"></bloatware>
  </bloatwareremoval>
  <registryedits skipsection="True">
    <regedit skip="False" filename="WindowsExplorerShowHiddenFiles.reg"     description="Set Windows Explorer to show hidden files and folders"></regedit>
    <regedit skip="False" filename="WindowsExplorerShowFileExtensions.reg"  description="Set Windows Explorer to show file extensions"></regedit>
    <regedit skip="False" filename="EnableDarkMode.reg"                     description="Enable Windows dark theme"></regedit>
    <regedit skip="False" filename="DisableSearchBoxWebResults.reg"         description="Disable web search in the start menu"></regedit>
    <regedit skip="False" filename="FixOneDriveDirectories.reg"             description="Fix OneDrive Directories"></regedit>
    <regedit skip="False" filename="DisableWindowsCopilot.reg"              description="Disable windows copilot"></regedit>
    <regedit skip="False" filename="DisableOneDriveSync.reg"                description="Disable OneDrive Sync"></regedit>
    <regedit skip="False" filename="UpdateConsoleLockDisplayOffTimeout.reg" description="Enable Update Console Lock Display off timeout"></regedit>
    <regedit skip="True"  filename="DisableUAC.reg"                         description="Disable UAC prompts"></regedit>
  </registryedits>
  <powersettings skipsection="True">
    <details>If running for the first time, current power settings will be backed up to local config directory</details>
    <details>If power settings backup already exists in local config directory it will be imported and set as current power settings</details>
  </powersettings>
  <backblazeclean skipsection="True">
    <details>This section adds lines to the Backblaze config file C:\ProgramData\Backblaze\bzdata\bzinfo.xml</details>
    <details>See README.md for more details</details>
    <dir skip="False" userdir="False" directory="C:\$SysReset" notes="The $SysReset folder is created when a Refresh or Reset operation fails. It contains a log folder that may be useful to system administrators experiencing a problem with refreshing or resetting a PC"></dir>
    <dir skip="False" userdir="False" directory="C:\Config.Msi" notes="The Config.Msi folder is used by the Windows Installer process during an installation of software. It saves files with the extension of .RBS and .RBF. These are Rollback Script Files used by the installer to uninstall recent changes if an install fails somewhere along the way"></dir>
    <dir skip="False" userdir="True"  directory="AppData\Local\Google" notes="This directory can easily be over 10 GB"></dir>
    <dir skip="False" userdir="True"  directory="AppData\Local\Microsoft\Internet Explorer"></dir>
  </backblazeclean>
  <setwallpaper skipsection="True">
    <details>This section sets the desktop wallpaper to an existing image in the local config wallpapers directory</details>
    <wallpaper>space.jpg</wallpaper>
  </setwallpaper>
  <disccleanup skipsection="True" firstrunonly="True">
    <details>Runs CleanMgr.exe with argument sagerun:1</details>
  </disccleanup>
  <chocoinstalls skipsection="True">
    <app skip="False" id="intel-xtu"                               description="Intel Extreme Tuning Utility (Intel XTU) is used to overclock, monitor, and stress a system"></app>
    <app skip="False" id="samsung-magician"                        description="Samsung Magician - Manage your drive like magic"></app>
  </chocoinstalls>
  <wingetinstalls skipsection="True">
    <app skip="False" id="Discord.Discord"                         description="Discord is an instant messaging and VoIP social platform which allows communication through voice calls, video calls, text messaging, and media"></app>
    <app skip="False" id="Git.Git"                                 description="Git is a distributed version control system that tracks versions of files"></app>
    <app skip="False" id="GitHub.GitHubDesktop"                    description="The ultimate GUI Git client for streamlining and enhancing your local code management process"></app>
    <app skip="False" id="Google.Chrome"                           description="Chrome is the official web browser from Google, built to be fast, secure, and customizable"></app>
    <app skip="False" id="Microsoft.VisualStudioCode"              description="Visual Studio Code, also commonly referred to as VS Code, is an integrated development environment developed by Microsoft for Windows, Linux, macOS and web browsers" override="/SILENT /mergetasks=&quot;!runcode,addcontextmenufiles,addcontextmenufolders&quot;"></app>
    <app skip="False" id="Mozilla.Firefox"                         description="Mozilla Firefox is a free and open source web browser developed by the Mozilla Foundation"></app>
    <app skip="False" id="SlackTechnologies.Slack"                 description="Slack is a cloud-based team communication platform developed by Slack Technologies"></app>
    <app skip="False" id="TheDocumentFoundation.LibreOffice"       description="LibreOffice is a free and open-source office productivity software suite, a project of The Document Foundation"></app>
  </wingetinstalls>
  <visualstudio skipsection="True">
    <details>Install Visual Studio Community</details>
    <options savesnapshots="True" installfromsnapshot="False"></options>
    <details>If savesnapshots is set True then current installation details will be saved to my.vsconfig file in local config directory during scheduled auto backup (requires Schedule Auto Backup of Settings to be enabled)</details>
    <details>If installfromsnapshot is set True then workload selections below will be ignored and installation preferences will be based off my.vsconfig snapshot</details>
    <app id="Microsoft.VisualStudio.2022.Community"   description="Visual Studio is an integrated development environment (IDE) developed by Microsoft. It is used to develop computer programs including websites, web apps, web services and mobile apps"></app>
    <workloaddetails website="https://learn.microsoft.com/en-us/visualstudio/install/workload-component-id-vs-community?view=vs-2022"></workloaddetails>
    <workloads>
      <workload skip="False" name="Azure development"                        id="Microsoft.VisualStudio.Workload.Azure"                 description="Azure SDKs, tools, and projects for developing cloud apps and creating resources using .NET and .NET Framework. Also includes tools for containerizing your application, including Docker support"></workload>
      <workload skip="False" name="Data storage and processing"              id="Microsoft.VisualStudio.Workload.Data"                  description="Connect, develop, and test data solutions with SQL Server, Azure Data Lake, or Hadoop"></workload>
      <workload skip="True"  name="Data science and analytical applications" id="Microsoft.VisualStudio.Workload.DataScience"           description="Languages and tooling for creating data science applications, including Python and F#"></workload>
      <workload skip="True"  name=".NET desktop development"                 id="Microsoft.VisualStudio.Workload.ManagedDesktop"        description="Build WPF, Windows Forms, and console applications using C#, Visual Basic, and F# with .NET and .NET Framework"></workload>
      <workload skip="True"  name="Game development with Unity"              id="Microsoft.VisualStudio.Workload.ManagedGame"           description="Create 2D and 3D games with Unity, a powerful cross-platform development environment"></workload>
      <workload skip="True"  name="Linux and embedded development with C++"  id="Microsoft.VisualStudio.Workload.NativeCrossPlat"       description="Create and debug applications running in a Linux environment or on an embedded device"></workload>
      <workload skip="True"  name="Desktop development with C++"             id="Microsoft.VisualStudio.Workload.NativeDesktop"         description="Build modern C++ apps for Windows using tools of your choice, including MSVC, Clang, CMake, or MSBuild"></workload>
      <workload skip="True"  name="Game development with C++"                id="Microsoft.VisualStudio.Workload.NativeGame"            description="Use the full power of C++ to build professional games powered by DirectX, Unreal, or Cocos2d"></workload>
      <workload skip="True"  name="Mobile development with C++"              id="Microsoft.VisualStudio.Workload.NativeMobile"          description="Build cross-platform applications for iOS, Android or Windows using C++"></workload>
      <workload skip="True"  name=".NET Multi-platform App UI development"   id="Microsoft.VisualStudio.Workload.NetCrossPlat"          description="Build Android, iOS, Windows, and Mac apps from a single codebase using C# with .NET MAUI"></workload>
      <workload skip="False" name="ASP.NET and web development"              id="Microsoft.VisualStudio.Workload.NetWeb"                description="Build web applications using ASP.NET Core, ASP.NET, HTML/JavaScript, and Containers including Docker support"></workload>
      <workload skip="False" name="Node.js development"                      id="Microsoft.VisualStudio.Workload.Node"                  description="Build scalable network applications using Node.js, an asynchronous event-driven JavaScript runtime"></workload>
      <workload skip="True"  name="Office/SharePoint development"            id="Microsoft.VisualStudio.Workload.Office"                description="Create Office and SharePoint add-ins, SharePoint solutions, and VSTO add-ins using C#, VB, and JavaScript"></workload>
      <workload skip="True"  name="Python development"                       id="Microsoft.VisualStudio.Workload.Python"                description="Editing, debugging, interactive development and source control for Python"></workload>
      <workload skip="True"  name="Windows application development"          id="Microsoft.VisualStudio.Workload.Universal"             description="Build applications for the Windows platform using WinUI with C# or optionally C++"></workload>
      <workload skip="True"  name="Visual Studio extension development"      id="Microsoft.VisualStudio.Workload.VisualStudioExtension" description="Create add-ons and extensions for Visual Studio, including new commands, code analyzers and tool windows"></workload>
    </workloads>
  </visualstudio>
  <setchromedefaultbrowser skipsection="True">
    <details>Sets Google Chrome as the default browser for Windows</details>
  </setchromedefaultbrowser>
  <appdatabackups>
    <backup skip="False" configfolder="DBeaver"        filename="data-sources.json" appdatadir="AppData\Roaming\DBeaverData\workspace6\General\.dbeaver\"                   description="DBeaver stores connection settings in this file, not passwords though"></backup>
    <backup skip="False" configfolder="TerminalConfig" filename="settings.json"     appdatadir="AppData\Local\Packages\Microsoft.WindowsTerminal_8wekyb3d8bbwe\LocalState\" description="Windows Terminal stores its profiles in this settings file"></backup>
  </appdatabackups>
  <gitrepositories>
    <gitrepo skip="False" name="lazyblaze" dest="C:\Code\" url="https://github.com/SuperBoots/lazyblaze.git" excludefrombackblaze="False"></gitrepo>
  </gitrepositories>
  <brokenshortcutremoval>
    <dir skip="False" userdir="True"  directory="Shortcuts\"                                    description="Custom location for storing shortcuts instead of the desktop"></dir>
    <dir skip="False" userdir="True"  directory="AppData\Roaming\Microsoft\Windows\Start Menu\" description="User specific location for shortcuts that are used in the Start Menu"></dir>
    <dir skip="False" userdir="False" directory="C:\ProgramData\Microsoft\Windows\Start Menu\"  description="Global location for shortcuts that are used in the Start Menu"></dir>
  </brokenshortcutremoval>
  <reviewed>False</reviewed>
</settings>